[
  {
    "date": "2014-07-23",
    "count": {
      "C#": {
        "nFiles": 39,
        "blank": 210,
        "comment": 210,
        "code": 1021
      },
      "PowerShell": {
        "nFiles": 3,
        "blank": 186,
        "comment": 725,
        "code": 566
      },
      "MSBuild script": {
        "nFiles": 3,
        "blank": 0,
        "comment": 20,
        "code": 324
      },
      "Pascal": {
        "nFiles": 1,
        "blank": 15,
        "comment": 69,
        "code": 29
      },
      "ASP.NET": {
        "nFiles": 1,
        "blank": 0,
        "comment": 0,
        "code": 1
      },
      "SUM": {
        "blank": 411,
        "comment": 1024,
        "code": 1941,
        "nFiles": 47
      }
    }
  },
  {
    "date": "2014-8-1",
    "count": {
      "C#": {
        "nFiles": 86,
        "blank": 420,
        "comment": 270,
        "code": 2630
      },
      "MSBuild script": {
        "nFiles": 5,
        "blank": 0,
        "comment": 34,
        "code": 617
      },
      "PowerShell": {
        "nFiles": 3,
        "blank": 186,
        "comment": 725,
        "code": 566
      },
      "ASP.NET": {
        "nFiles": 1,
        "blank": 0,
        "comment": 0,
        "code": 1
      },
      "SUM": {
        "blank": 606,
        "comment": 1029,
        "code": 3814,
        "nFiles": 95
      }
    }
  },
  {
    "date": "2014-9-1",
    "count": {
      "C#": {
        "nFiles": 116,
        "blank": 729,
        "comment": 406,
        "code": 5290
      },
      "MSBuild script": {
        "nFiles": 6,
        "blank": 0,
        "comment": 41,
        "code": 702
      },
      "PowerShell": {
        "nFiles": 3,
        "blank": 186,
        "comment": 725,
        "code": 566
      },
      "ASP.NET": {
        "nFiles": 1,
        "blank": 0,
        "comment": 0,
        "code": 1
      },
      "SUM": {
        "blank": 915,
        "comment": 1172,
        "code": 6559,
        "nFiles": 126
      }
    }
  },
  {
    "date": "2014-10-1",
    "count": {
      "C#": {
        "nFiles": 135,
        "blank": 872,
        "comment": 785,
        "code": 6995
      },
      "MSBuild script": {
        "nFiles": 6,
        "blank": 0,
        "comment": 41,
        "code": 728
      },
      "PowerShell": {
        "nFiles": 3,
        "blank": 186,
        "comment": 725,
        "code": 566
      },
      "ASP.NET": {
        "nFiles": 1,
        "blank": 0,
        "comment": 0,
        "code": 1
      },
      "SUM": {
        "blank": 1058,
        "comment": 1551,
        "code": 8290,
        "nFiles": 145
      }
    }
  },
  {
    "date": "2014-11-1",
    "count": {
      "C#": {
        "nFiles": 206,
        "blank": 1154,
        "comment": 763,
        "code": 10603
      },
      "MSBuild script": {
        "nFiles": 6,
        "blank": 0,
        "comment": 41,
        "code": 855
      },
      "PowerShell": {
        "nFiles": 3,
        "blank": 186,
        "comment": 725,
        "code": 566
      },
      "ASP.NET": {
        "nFiles": 1,
        "blank": 0,
        "comment": 0,
        "code": 1
      },
      "SUM": {
        "blank": 1340,
        "comment": 1529,
        "code": 12025,
        "nFiles": 216
      }
    }
  },
  {
    "date": "2014-12-1",
    "count": {
      "C#": {
        "nFiles": 235,
        "blank": 1309,
        "comment": 740,
        "code": 12481
      },
      "MSBuild script": {
        "nFiles": 6,
        "blank": 0,
        "comment": 41,
        "code": 912
      },
      "PowerShell": {
        "nFiles": 3,
        "blank": 186,
        "comment": 725,
        "code": 566
      },
      "Smalltalk": {
        "nFiles": 1,
        "blank": 22,
        "comment": 28,
        "code": 333
      },
      "ASP.NET": {
        "nFiles": 1,
        "blank": 0,
        "comment": 0,
        "code": 1
      },
      "SUM": {
        "blank": 1517,
        "comment": 1534,
        "code": 14293,
        "nFiles": 246
      }
    }
  },
  {
    "date": "2015-1-1",
    "count": {
      "C#": {
        "nFiles": 286,
        "blank": 1545,
        "comment": 754,
        "code": 14675
      },
      "MSBuild script": {
        "nFiles": 6,
        "blank": 0,
        "comment": 41,
        "code": 1035
      },
      "PowerShell": {
        "nFiles": 3,
        "blank": 186,
        "comment": 725,
        "code": 566
      },
      "Smalltalk": {
        "nFiles": 1,
        "blank": 22,
        "comment": 28,
        "code": 333
      },
      "ASP.NET": {
        "nFiles": 1,
        "blank": 0,
        "comment": 0,
        "code": 1
      },
      "SUM": {
        "blank": 1753,
        "comment": 1548,
        "code": 16610,
        "nFiles": 297
      }
    }
  },
  {
    "date": "2015-2-1",
    "count": {
      "C#": {
        "nFiles": 349,
        "blank": 1966,
        "comment": 862,
        "code": 18294
      },
      "MSBuild script": {
        "nFiles": 10,
        "blank": 0,
        "comment": 69,
        "code": 1478
      },
      "PowerShell": {
        "nFiles": 3,
        "blank": 186,
        "comment": 725,
        "code": 566
      },
      "Smalltalk": {
        "nFiles": 1,
        "blank": 2,
        "comment": 0,
        "code": 95
      },
      "ASP.NET": {
        "nFiles": 1,
        "blank": 0,
        "comment": 0,
        "code": 1
      },
      "SUM": {
        "blank": 2154,
        "comment": 1656,
        "code": 20434,
        "nFiles": 364
      }
    }
  },
  {
    "date": "2015-3-1",
    "count": {
      "C#": {
        "nFiles": 384,
        "blank": 2266,
        "comment": 866,
        "code": 20385
      },
      "MSBuild script": {
        "nFiles": 10,
        "blank": 0,
        "comment": 69,
        "code": 1634
      },
      "PowerShell": {
        "nFiles": 4,
        "blank": 209,
        "comment": 736,
        "code": 625
      },
      "Smalltalk": {
        "nFiles": 1,
        "blank": 2,
        "comment": 0,
        "code": 99
      },
      "ASP.NET": {
        "nFiles": 1,
        "blank": 0,
        "comment": 0,
        "code": 1
      },
      "SUM": {
        "blank": 2477,
        "comment": 1671,
        "code": 22744,
        "nFiles": 400
      }
    }
  },
  {
    "date": "2015-4-1",
    "count": {
      "C#": {
        "nFiles": 393,
        "blank": 2349,
        "comment": 865,
        "code": 21196
      },
      "MSBuild script": {
        "nFiles": 10,
        "blank": 0,
        "comment": 69,
        "code": 1732
      },
      "PowerShell": {
        "nFiles": 4,
        "blank": 209,
        "comment": 736,
        "code": 625
      },
      "Smalltalk": {
        "nFiles": 1,
        "blank": 2,
        "comment": 0,
        "code": 95
      },
      "Razor": {
        "nFiles": 1,
        "blank": 0,
        "comment": 0,
        "code": 1
      },
      "ASP.NET": {
        "nFiles": 1,
        "blank": 0,
        "comment": 0,
        "code": 1
      },
      "SUM": {
        "blank": 2560,
        "comment": 1670,
        "code": 23650,
        "nFiles": 410
      }
    }
  },
  {
    "date": "2015-5-1",
    "count": {
      "C#": {
        "nFiles": 439,
        "blank": 2573,
        "comment": 880,
        "code": 23040
      },
      "MSBuild script": {
        "nFiles": 10,
        "blank": 0,
        "comment": 69,
        "code": 1814
      },
      "PowerShell": {
        "nFiles": 4,
        "blank": 209,
        "comment": 736,
        "code": 625
      },
      "Smalltalk": {
        "nFiles": 2,
        "blank": 8,
        "comment": 276,
        "code": 112
      },
      "ASP.NET": {
        "nFiles": 1,
        "blank": 0,
        "comment": 0,
        "code": 1
      },
      "Razor": {
        "nFiles": 1,
        "blank": 0,
        "comment": 0,
        "code": 1
      },
      "SUM": {
        "blank": 2790,
        "comment": 1961,
        "code": 25593,
        "nFiles": 457
      }
    }
  },
  {
    "date": "2015-6-1",
    "count": {
      "C#": {
        "nFiles": 457,
        "blank": 2636,
        "comment": 885,
        "code": 23714
      },
      "MSBuild script": {
        "nFiles": 10,
        "blank": 0,
        "comment": 69,
        "code": 1857
      },
      "PowerShell": {
        "nFiles": 4,
        "blank": 209,
        "comment": 736,
        "code": 625
      },
      "Smalltalk": {
        "nFiles": 2,
        "blank": 9,
        "comment": 276,
        "code": 119
      },
      "ASP.NET": {
        "nFiles": 1,
        "blank": 0,
        "comment": 0,
        "code": 1
      },
      "Razor": {
        "nFiles": 1,
        "blank": 0,
        "comment": 0,
        "code": 1
      },
      "SUM": {
        "blank": 2854,
        "comment": 1966,
        "code": 26317,
        "nFiles": 475
      }
    }
  },
  {
    "date": "2015-7-1",
    "count": {
      "C#": {
        "nFiles": 470,
        "blank": 2785,
        "comment": 892,
        "code": 24990
      },
      "MSBuild script": {
        "nFiles": 10,
        "blank": 0,
        "comment": 69,
        "code": 1938
      },
      "PowerShell": {
        "nFiles": 4,
        "blank": 209,
        "comment": 736,
        "code": 625
      },
      "Smalltalk": {
        "nFiles": 2,
        "blank": 9,
        "comment": 276,
        "code": 119
      },
      "Razor": {
        "nFiles": 1,
        "blank": 0,
        "comment": 0,
        "code": 1
      },
      "ASP.NET": {
        "nFiles": 1,
        "blank": 0,
        "comment": 0,
        "code": 1
      },
      "SUM": {
        "blank": 3003,
        "comment": 1973,
        "code": 27674,
        "nFiles": 488
      }
    }
  },
  {
    "date": "2015-8-1",
    "count": {
      "C#": {
        "nFiles": 475,
        "blank": 2816,
        "comment": 921,
        "code": 25350
      },
      "MSBuild script": {
        "nFiles": 11,
        "blank": 0,
        "comment": 76,
        "code": 2062
      },
      "PowerShell": {
        "nFiles": 4,
        "blank": 209,
        "comment": 736,
        "code": 625
      },
      "Smalltalk": {
        "nFiles": 2,
        "blank": 9,
        "comment": 276,
        "code": 119
      },
      "Razor": {
        "nFiles": 1,
        "blank": 0,
        "comment": 0,
        "code": 1
      },
      "ASP.NET": {
        "nFiles": 1,
        "blank": 0,
        "comment": 0,
        "code": 1
      },
      "SUM": {
        "blank": 3034,
        "comment": 2009,
        "code": 28158,
        "nFiles": 494
      }
    }
  },
  {
    "date": "2015-9-1",
    "count": {
      "C#": {
        "nFiles": 492,
        "blank": 2957,
        "comment": 910,
        "code": 26560
      },
      "MSBuild script": {
        "nFiles": 11,
        "blank": 0,
        "comment": 76,
        "code": 2086
      },
      "PowerShell": {
        "nFiles": 4,
        "blank": 209,
        "comment": 736,
        "code": 625
      },
      "Smalltalk": {
        "nFiles": 2,
        "blank": 9,
        "comment": 276,
        "code": 119
      },
      "Razor": {
        "nFiles": 1,
        "blank": 0,
        "comment": 0,
        "code": 1
      },
      "ASP.NET": {
        "nFiles": 1,
        "blank": 0,
        "comment": 0,
        "code": 1
      },
      "SUM": {
        "blank": 3175,
        "comment": 1998,
        "code": 29392,
        "nFiles": 511
      }
    }
  },
  {
    "date": "2015-10-1",
    "count": {
      "C#": {
        "nFiles": 492,
        "blank": 2995,
        "comment": 910,
        "code": 26897
      },
      "MSBuild script": {
        "nFiles": 11,
        "blank": 0,
        "comment": 76,
        "code": 2107
      },
      "PowerShell": {
        "nFiles": 4,
        "blank": 209,
        "comment": 736,
        "code": 625
      },
      "Smalltalk": {
        "nFiles": 1,
        "blank": 6,
        "comment": 276,
        "code": 15
      },
      "Razor": {
        "nFiles": 1,
        "blank": 0,
        "comment": 0,
        "code": 1
      },
      "ASP.NET": {
        "nFiles": 1,
        "blank": 0,
        "comment": 0,
        "code": 1
      },
      "SUM": {
        "blank": 3210,
        "comment": 1998,
        "code": 29646,
        "nFiles": 510
      }
    }
  },
  {
    "date": "2015-11-1",
    "count": {
      "C#": {
        "nFiles": 499,
        "blank": 3104,
        "comment": 923,
        "code": 27741
      },
      "MSBuild script": {
        "nFiles": 11,
        "blank": 0,
        "comment": 76,
        "code": 2114
      },
      "PowerShell": {
        "nFiles": 4,
        "blank": 209,
        "comment": 736,
        "code": 625
      },
      "Smalltalk": {
        "nFiles": 1,
        "blank": 6,
        "comment": 276,
        "code": 15
      },
      "ASP.NET": {
        "nFiles": 1,
        "blank": 0,
        "comment": 0,
        "code": 1
      },
      "Razor": {
        "nFiles": 1,
        "blank": 0,
        "comment": 0,
        "code": 1
      },
      "SUM": {
        "blank": 3319,
        "comment": 2011,
        "code": 30497,
        "nFiles": 517
      }
    }
  },
  {
    "date": "2015-12-1",
    "count": {
      "C#": {
        "nFiles": 535,
        "blank": 3271,
        "comment": 909,
        "code": 29255
      },
      "MSBuild script": {
        "nFiles": 12,
        "blank": 0,
        "comment": 83,
        "code": 2222
      },
      "PowerShell": {
        "nFiles": 4,
        "blank": 209,
        "comment": 736,
        "code": 625
      },
      "Smalltalk": {
        "nFiles": 1,
        "blank": 6,
        "comment": 276,
        "code": 15
      },
      "Razor": {
        "nFiles": 1,
        "blank": 0,
        "comment": 0,
        "code": 1
      },
      "ASP.NET": {
        "nFiles": 1,
        "blank": 0,
        "comment": 0,
        "code": 1
      },
      "SUM": {
        "blank": 3486,
        "comment": 2004,
        "code": 32119,
        "nFiles": 554
      }
    }
  },
  {
    "date": "2016-1-1",
    "count": {
      "C#": {
        "nFiles": 555,
        "blank": 3335,
        "comment": 910,
        "code": 29838
      },
      "MSBuild script": {
        "nFiles": 12,
        "blank": 0,
        "comment": 83,
        "code": 2254
      },
      "PowerShell": {
        "nFiles": 4,
        "blank": 209,
        "comment": 736,
        "code": 625
      },
      "Smalltalk": {
        "nFiles": 1,
        "blank": 6,
        "comment": 276,
        "code": 15
      },
      "ASP.NET": {
        "nFiles": 1,
        "blank": 0,
        "comment": 0,
        "code": 1
      },
      "Razor": {
        "nFiles": 1,
        "blank": 0,
        "comment": 0,
        "code": 1
      },
      "SUM": {
        "blank": 3550,
        "comment": 2005,
        "code": 32734,
        "nFiles": 574
      }
    }
  },
  {
    "date": "2016-2-1",
    "count": {
      "C#": {
        "nFiles": 566,
        "blank": 3432,
        "comment": 914,
        "code": 30479
      },
      "MSBuild script": {
        "nFiles": 12,
        "blank": 0,
        "comment": 83,
        "code": 2274
      },
      "PowerShell": {
        "nFiles": 4,
        "blank": 209,
        "comment": 736,
        "code": 625
      },
      "Smalltalk": {
        "nFiles": 1,
        "blank": 6,
        "comment": 276,
        "code": 15
      },
      "ASP.NET": {
        "nFiles": 1,
        "blank": 0,
        "comment": 0,
        "code": 1
      },
      "Razor": {
        "nFiles": 1,
        "blank": 0,
        "comment": 0,
        "code": 1
      },
      "SUM": {
        "blank": 3647,
        "comment": 2009,
        "code": 33395,
        "nFiles": 585
      }
    }
  },
  {
    "date": "2016-3-1",
    "count": {
      "C#": {
        "nFiles": 577,
        "blank": 3456,
        "comment": 920,
        "code": 30806
      },
      "MSBuild script": {
        "nFiles": 12,
        "blank": 0,
        "comment": 83,
        "code": 2286
      },
      "PowerShell": {
        "nFiles": 4,
        "blank": 209,
        "comment": 736,
        "code": 625
      },
      "Smalltalk": {
        "nFiles": 1,
        "blank": 6,
        "comment": 276,
        "code": 15
      },
      "ASP.NET": {
        "nFiles": 1,
        "blank": 0,
        "comment": 0,
        "code": 1
      },
      "Razor": {
        "nFiles": 1,
        "blank": 0,
        "comment": 0,
        "code": 1
      },
      "SUM": {
        "blank": 3671,
        "comment": 2015,
        "code": 33734,
        "nFiles": 596
      }
    }
  },
  {
    "date": "2016-4-1",
    "count": {
      "C#": {
        "nFiles": 590,
        "blank": 3526,
        "comment": 937,
        "code": 31414
      },
      "MSBuild script": {
        "nFiles": 13,
        "blank": 0,
        "comment": 90,
        "code": 2395
      },
      "PowerShell": {
        "nFiles": 4,
        "blank": 209,
        "comment": 736,
        "code": 625
      },
      "Smalltalk": {
        "nFiles": 1,
        "blank": 6,
        "comment": 276,
        "code": 15
      },
      "Razor": {
        "nFiles": 1,
        "blank": 0,
        "comment": 0,
        "code": 1
      },
      "ASP.NET": {
        "nFiles": 1,
        "blank": 0,
        "comment": 0,
        "code": 1
      },
      "SUM": {
        "blank": 3741,
        "comment": 2039,
        "code": 34451,
        "nFiles": 610
      }
    }
  },
  {
    "date": "2016-5-1",
    "count": {
      "C#": {
        "nFiles": 596,
        "blank": 3574,
        "comment": 938,
        "code": 31833
      },
      "MSBuild script": {
        "nFiles": 13,
        "blank": 0,
        "comment": 90,
        "code": 2401
      },
      "PowerShell": {
        "nFiles": 4,
        "blank": 209,
        "comment": 736,
        "code": 625
      },
      "Smalltalk": {
        "nFiles": 1,
        "blank": 6,
        "comment": 276,
        "code": 15
      },
      "Razor": {
        "nFiles": 1,
        "blank": 0,
        "comment": 0,
        "code": 1
      },
      "ASP.NET": {
        "nFiles": 1,
        "blank": 0,
        "comment": 0,
        "code": 1
      },
      "SUM": {
        "blank": 3789,
        "comment": 2040,
        "code": 34876,
        "nFiles": 616
      }
    }
  },
  {
    "date": "2016-6-1",
    "count": {
      "C#": {
        "nFiles": 631,
        "blank": 3820,
        "comment": 1085,
        "code": 33395
      },
      "MSBuild script": {
        "nFiles": 15,
        "blank": 0,
        "comment": 104,
        "code": 2668
      },
      "PowerShell": {
        "nFiles": 4,
        "blank": 209,
        "comment": 736,
        "code": 625
      },
      "Smalltalk": {
        "nFiles": 1,
        "blank": 6,
        "comment": 276,
        "code": 15
      },
      "Razor": {
        "nFiles": 1,
        "blank": 0,
        "comment": 0,
        "code": 1
      },
      "ASP.NET": {
        "nFiles": 1,
        "blank": 0,
        "comment": 0,
        "code": 1
      },
      "SUM": {
        "blank": 4035,
        "comment": 2201,
        "code": 36705,
        "nFiles": 653
      }
    }
  },
  {
    "date": "2016-7-1",
    "count": {
      "C#": {
        "nFiles": 656,
        "blank": 4143,
        "comment": 1099,
        "code": 35048
      },
      "MSBuild script": {
        "nFiles": 15,
        "blank": 0,
        "comment": 104,
        "code": 2423
      },
      "PowerShell": {
        "nFiles": 4,
        "blank": 209,
        "comment": 736,
        "code": 625
      },
      "Smalltalk": {
        "nFiles": 2,
        "blank": 17,
        "comment": 276,
        "code": 81
      },
      "ASP.NET": {
        "nFiles": 1,
        "blank": 0,
        "comment": 0,
        "code": 1
      },
      "Razor": {
        "nFiles": 1,
        "blank": 0,
        "comment": 0,
        "code": 1
      },
      "SUM": {
        "blank": 4369,
        "comment": 2215,
        "code": 38179,
        "nFiles": 679
      }
    }
  },
  {
    "date": "2016-8-1",
    "count": {
      "C#": {
        "nFiles": 704,
        "blank": 4578,
        "comment": 1153,
        "code": 37950
      },
      "MSBuild script": {
        "nFiles": 15,
        "blank": 0,
        "comment": 104,
        "code": 2522
      },
      "PowerShell": {
        "nFiles": 7,
        "blank": 215,
        "comment": 736,
        "code": 676
      },
      "Smalltalk": {
        "nFiles": 4,
        "blank": 27,
        "comment": 433,
        "code": 197
      },
      "ASP.NET": {
        "nFiles": 1,
        "blank": 0,
        "comment": 0,
        "code": 1
      },
      "Razor": {
        "nFiles": 1,
        "blank": 0,
        "comment": 0,
        "code": 1
      },
      "SUM": {
        "blank": 4820,
        "comment": 2426,
        "code": 41347,
        "nFiles": 732
      }
    }
  },
  {
    "date": "2016-9-1",
    "count": {
      "C#": {
        "nFiles": 715,
        "blank": 4810,
        "comment": 1130,
        "code": 40066
      },
      "MSBuild script": {
        "nFiles": 15,
        "blank": 0,
        "comment": 104,
        "code": 2533
      },
      "PowerShell": {
        "nFiles": 7,
        "blank": 215,
        "comment": 736,
        "code": 676
      },
      "Smalltalk": {
        "nFiles": 4,
        "blank": 27,
        "comment": 433,
        "code": 197
      },
      "ASP.NET": {
        "nFiles": 1,
        "blank": 0,
        "comment": 0,
        "code": 1
      },
      "Razor": {
        "nFiles": 1,
        "blank": 0,
        "comment": 0,
        "code": 1
      },
      "SUM": {
        "blank": 5052,
        "comment": 2403,
        "code": 43474,
        "nFiles": 743
      }
    }
  },
  {
    "date": "2016-10-1",
    "count": {
      "C#": {
        "nFiles": 764,
        "blank": 5348,
        "comment": 1221,
        "code": 43323
      },
      "MSBuild script": {
        "nFiles": 16,
        "blank": 0,
        "comment": 111,
        "code": 2664
      },
      "PowerShell": {
        "nFiles": 7,
        "blank": 215,
        "comment": 736,
        "code": 676
      },
      "Smalltalk": {
        "nFiles": 4,
        "blank": 27,
        "comment": 433,
        "code": 205
      },
      "Razor": {
        "nFiles": 1,
        "blank": 0,
        "comment": 0,
        "code": 1
      },
      "ASP.NET": {
        "nFiles": 1,
        "blank": 0,
        "comment": 0,
        "code": 1
      },
      "SUM": {
        "blank": 5590,
        "comment": 2501,
        "code": 46870,
        "nFiles": 793
      }
    }
  },
  {
    "date": "2016-11-1",
    "count": {
      "C#": {
        "nFiles": 867,
        "blank": 6176,
        "comment": 1291,
        "code": 51643
      },
      "MSBuild script": {
        "nFiles": 19,
        "blank": 0,
        "comment": 132,
        "code": 3185
      },
      "PowerShell": {
        "nFiles": 7,
        "blank": 215,
        "comment": 736,
        "code": 676
      },
      "Smalltalk": {
        "nFiles": 4,
        "blank": 36,
        "comment": 433,
        "code": 234
      },
      "Razor": {
        "nFiles": 8,
        "blank": 4,
        "comment": 1,
        "code": 112
      },
      "ASP.NET": {
        "nFiles": 2,
        "blank": 0,
        "comment": 0,
        "code": 2
      },
      "SUM": {
        "blank": 6431,
        "comment": 2593,
        "code": 55852,
        "nFiles": 907
      }
    }
  },
  {
    "date": "2016-12-1",
    "count": {
      "C#": {
        "nFiles": 927,
        "blank": 6628,
        "comment": 1391,
        "code": 57657
      },
      "MSBuild script": {
        "nFiles": 21,
        "blank": 0,
        "comment": 146,
        "code": 3414
      },
      "PowerShell": {
        "nFiles": 7,
        "blank": 215,
        "comment": 736,
        "code": 676
      },
      "Smalltalk": {
        "nFiles": 4,
        "blank": 36,
        "comment": 433,
        "code": 234
      },
      "Razor": {
        "nFiles": 8,
        "blank": 4,
        "comment": 1,
        "code": 112
      },
      "ASP.NET": {
        "nFiles": 2,
        "blank": 0,
        "comment": 0,
        "code": 2
      },
      "SUM": {
        "blank": 6883,
        "comment": 2707,
        "code": 62095,
        "nFiles": 969
      }
    }
  },
  {
    "date": "2017-1-1",
    "count": {
      "C#": {
        "nFiles": 956,
        "blank": 6885,
        "comment": 1384,
        "code": 62061
      },
      "MSBuild script": {
        "nFiles": 22,
        "blank": 0,
        "comment": 153,
        "code": 3570
      },
      "PowerShell": {
        "nFiles": 7,
        "blank": 215,
        "comment": 736,
        "code": 677
      },
      "Smalltalk": {
        "nFiles": 4,
        "blank": 36,
        "comment": 433,
        "code": 234
      },
      "Razor": {
        "nFiles": 8,
        "blank": 4,
        "comment": 1,
        "code": 112
      },
      "HTML": {
        "nFiles": 1,
        "blank": 1,
        "comment": 0,
        "code": 46
      },
      "ASP.NET": {
        "nFiles": 2,
        "blank": 0,
        "comment": 0,
        "code": 2
      },
      "SUM": {
        "blank": 7141,
        "comment": 2707,
        "code": 66702,
        "nFiles": 1000
      }
    }
  },
  {
    "date": "2017-2-1",
    "count": {
      "C#": {
        "nFiles": 978,
        "blank": 7065,
        "comment": 1390,
        "code": 63465
      },
      "MSBuild script": {
        "nFiles": 22,
        "blank": 0,
        "comment": 153,
        "code": 3601
      },
      "PowerShell": {
        "nFiles": 7,
        "blank": 215,
        "comment": 736,
        "code": 677
      },
      "Smalltalk": {
        "nFiles": 4,
        "blank": 38,
        "comment": 433,
        "code": 240
      },
      "Razor": {
        "nFiles": 8,
        "blank": 4,
        "comment": 1,
        "code": 112
      },
      "HTML": {
        "nFiles": 1,
        "blank": 1,
        "comment": 0,
        "code": 46
      },
      "ASP.NET": {
        "nFiles": 2,
        "blank": 0,
        "comment": 0,
        "code": 2
      },
      "SUM": {
        "blank": 7323,
        "comment": 2713,
        "code": 68143,
        "nFiles": 1022
      }
    }
  },
  {
    "date": "2017-3-1",
    "count": {
      "C#": {
        "nFiles": 962,
        "blank": 6917,
        "comment": 1366,
        "code": 62328
      },
      "MSBuild script": {
        "nFiles": 22,
        "blank": 0,
        "comment": 153,
        "code": 3583
      },
      "PowerShell": {
        "nFiles": 7,
        "blank": 215,
        "comment": 736,
        "code": 677
      },
      "Smalltalk": {
        "nFiles": 4,
        "blank": 37,
        "comment": 433,
        "code": 236
      },
      "Razor": {
        "nFiles": 8,
        "blank": 4,
        "comment": 1,
        "code": 112
      },
      "HTML": {
        "nFiles": 1,
        "blank": 1,
        "comment": 0,
        "code": 46
      },
      "ASP.NET": {
        "nFiles": 2,
        "blank": 0,
        "comment": 0,
        "code": 2
      },
      "SUM": {
        "blank": 7174,
        "comment": 2689,
        "code": 66984,
        "nFiles": 1006
      }
    }
  },
  {
    "date": "2017-4-1",
    "count": {
      "C#": {
        "nFiles": 1061,
        "blank": 7745,
        "comment": 1405,
        "code": 72725
      },
      "MSBuild script": {
        "nFiles": 23,
        "blank": 0,
        "comment": 160,
        "code": 4436
      },
      "PowerShell": {
        "nFiles": 7,
        "blank": 215,
        "comment": 736,
        "code": 677
      },
      "C++": {
        "nFiles": 3,
        "blank": 58,
        "comment": 19,
        "code": 329
      },
      "Smalltalk": {
        "nFiles": 4,
        "blank": 37,
        "comment": 433,
        "code": 242
      },
      "Razor": {
        "nFiles": 8,
        "blank": 4,
        "comment": 1,
        "code": 112
      },
      "HTML": {
        "nFiles": 1,
        "blank": 1,
        "comment": 0,
        "code": 46
      },
      "C/C++ Header": {
        "nFiles": 2,
        "blank": 5,
        "comment": 4,
        "code": 28
      },
      "ASP.NET": {
        "nFiles": 2,
        "blank": 0,
        "comment": 0,
        "code": 2
      },
      "SUM": {
        "blank": 8065,
        "comment": 2758,
        "code": 78597,
        "nFiles": 1111
      }
    }
  },
  {
    "date": "2017-5-1",
    "count": {
      "C#": {
        "nFiles": 1043,
        "blank": 7419,
        "comment": 1197,
        "code": 69919
      },
      "MSBuild script": {
        "nFiles": 21,
        "blank": 0,
        "comment": 146,
        "code": 4220
      },
      "PowerShell": {
        "nFiles": 7,
        "blank": 215,
        "comment": 736,
        "code": 679
      },
      "C++": {
        "nFiles": 3,
        "blank": 58,
        "comment": 19,
        "code": 329
      },
      "Smalltalk": {
        "nFiles": 4,
        "blank": 38,
        "comment": 433,
        "code": 244
      },
      "Razor": {
        "nFiles": 8,
        "blank": 4,
        "comment": 1,
        "code": 112
      },
      "HTML": {
        "nFiles": 1,
        "blank": 1,
        "comment": 0,
        "code": 46
      },
      "C/C++ Header": {
        "nFiles": 2,
        "blank": 5,
        "comment": 4,
        "code": 28
      },
      "ASP.NET": {
        "nFiles": 2,
        "blank": 0,
        "comment": 0,
        "code": 2
      },
      "SUM": {
        "blank": 7740,
        "comment": 2536,
        "code": 75579,
        "nFiles": 1091
      }
    }
  },
  {
    "date": "2017-6-1",
    "count": {
      "C#": {
        "nFiles": 1072,
        "blank": 7625,
        "comment": 1248,
        "code": 71474
      },
      "C++": {
        "nFiles": 48,
        "blank": 935,
        "comment": 76,
        "code": 6252
      },
      "MSBuild script": {
        "nFiles": 22,
        "blank": 0,
        "comment": 153,
        "code": 4410
      },
      "C/C++ Header": {
        "nFiles": 92,
        "blank": 722,
        "comment": 143,
        "code": 4121
      },
      "PowerShell": {
        "nFiles": 7,
        "blank": 215,
        "comment": 736,
        "code": 679
      },
      "Smalltalk": {
        "nFiles": 4,
        "blank": 28,
        "comment": 433,
        "code": 238
      },
      "Razor": {
        "nFiles": 10,
        "blank": 5,
        "comment": 0,
        "code": 196
      },
      "CSS": {
        "nFiles": 1,
        "blank": 33,
        "comment": 0,
        "code": 190
      },
      "HTML": {
        "nFiles": 1,
        "blank": 1,
        "comment": 0,
        "code": 46
      },
      "ASP.NET": {
        "nFiles": 2,
        "blank": 0,
        "comment": 0,
        "code": 2
      },
      "SUM": {
        "blank": 9564,
        "comment": 2789,
        "code": 87608,
        "nFiles": 1259
      }
    }
  },
  {
    "date": "2017-7-1",
    "count": {
      "C#": {
        "nFiles": 1093,
        "blank": 7821,
        "comment": 1253,
        "code": 73037
      },
      "C++": {
        "nFiles": 51,
        "blank": 1008,
        "comment": 58,
        "code": 6916
      },
      "MSBuild script": {
        "nFiles": 22,
        "blank": 0,
        "comment": 153,
        "code": 4552
      },
      "C/C++ Header": {
        "nFiles": 95,
        "blank": 756,
        "comment": 121,
        "code": 4223
      },
      "PowerShell": {
        "nFiles": 7,
        "blank": 215,
        "comment": 736,
        "code": 679
      },
      "Smalltalk": {
        "nFiles": 2,
        "blank": 13,
        "comment": 0,
        "code": 199
      },
      "Razor": {
        "nFiles": 10,
        "blank": 5,
        "comment": 0,
        "code": 196
      },
      "CSS": {
        "nFiles": 1,
        "blank": 33,
        "comment": 0,
        "code": 190
      },
      "HTML": {
        "nFiles": 1,
        "blank": 1,
        "comment": 0,
        "code": 46
      },
      "ASP.NET": {
        "nFiles": 2,
        "blank": 0,
        "comment": 0,
        "code": 2
      },
      "SUM": {
        "blank": 9852,
        "comment": 2321,
        "code": 90040,
        "nFiles": 1284
      }
    }
  },
  {
    "date": "2017-8-1",
    "count": {
      "C#": {
        "nFiles": 936,
        "blank": 6747,
        "comment": 1103,
        "code": 53711
      },
      "C++": {
        "nFiles": 51,
        "blank": 1008,
        "comment": 58,
        "code": 6916
      },
      "C/C++ Header": {
        "nFiles": 95,
        "blank": 755,
        "comment": 119,
        "code": 4239
      },
      "MSBuild script": {
        "nFiles": 19,
        "blank": 0,
        "comment": 132,
        "code": 3985
      },
      "PowerShell": {
        "nFiles": 9,
        "blank": 231,
        "comment": 739,
        "code": 776
      },
      "Smalltalk": {
        "nFiles": 2,
        "blank": 13,
        "comment": 0,
        "code": 199
      },
      "Razor": {
        "nFiles": 10,
        "blank": 5,
        "comment": 0,
        "code": 196
      },
      "CSS": {
        "nFiles": 1,
        "blank": 33,
        "comment": 0,
        "code": 190
      },
      "Markdown": {
        "nFiles": 2,
        "blank": 23,
        "comment": 0,
        "code": 88
      },
      "HTML": {
        "nFiles": 1,
        "blank": 1,
        "comment": 0,
        "code": 46
      },
      "ASP.NET": {
        "nFiles": 2,
        "blank": 0,
        "comment": 0,
        "code": 2
      },
      "SUM": {
        "blank": 8816,
        "comment": 2151,
        "code": 70348,
        "nFiles": 1128
      }
    }
  },
  {
    "date": "2017-9-1",
    "count": {
      "C#": {
        "nFiles": 939,
        "blank": 6820,
        "comment": 1103,
        "code": 54346
      },
      "C++": {
        "nFiles": 51,
        "blank": 1014,
        "comment": 58,
        "code": 6993
      },
      "C/C++ Header": {
        "nFiles": 97,
        "blank": 1297,
        "comment": 415,
        "code": 5861
      },
      "MSBuild script": {
        "nFiles": 19,
        "blank": 0,
        "comment": 132,
        "code": 3994
      },
      "PowerShell": {
        "nFiles": 7,
        "blank": 222,
        "comment": 737,
        "code": 709
      },
      "Smalltalk": {
        "nFiles": 2,
        "blank": 13,
        "comment": 0,
        "code": 201
      },
      "Razor": {
        "nFiles": 10,
        "blank": 5,
        "comment": 0,
        "code": 196
      },
      "CSS": {
        "nFiles": 1,
        "blank": 33,
        "comment": 0,
        "code": 190
      },
      "HTML": {
        "nFiles": 1,
        "blank": 1,
        "comment": 0,
        "code": 46
      },
      "Markdown": {
        "nFiles": 1,
        "blank": 4,
        "comment": 0,
        "code": 16
      },
      "ASP.NET": {
        "nFiles": 2,
        "blank": 0,
        "comment": 0,
        "code": 2
      },
      "SUM": {
        "blank": 9409,
        "comment": 2445,
        "code": 72554,
        "nFiles": 1130
      }
    }
  },
  {
    "date": "2017-10-1",
    "count": {
      "C#": {
        "nFiles": 982,
        "blank": 7185,
        "comment": 2171,
        "code": 55613
      },
      "C++": {
        "nFiles": 53,
        "blank": 1026,
        "comment": 76,
        "code": 7021
      },
      "C/C++ Header": {
        "nFiles": 99,
        "blank": 1301,
        "comment": 423,
        "code": 5870
      },
      "MSBuild script": {
        "nFiles": 22,
        "blank": 0,
        "comment": 153,
        "code": 4455
      },
      "PowerShell": {
        "nFiles": 7,
        "blank": 222,
        "comment": 737,
        "code": 709
      },
      "Smalltalk": {
        "nFiles": 2,
        "blank": 13,
        "comment": 0,
        "code": 201
      },
      "Razor": {
        "nFiles": 10,
        "blank": 5,
        "comment": 0,
        "code": 196
      },
      "CSS": {
        "nFiles": 1,
        "blank": 33,
        "comment": 0,
        "code": 190
      },
      "HTML": {
        "nFiles": 1,
        "blank": 1,
        "comment": 0,
        "code": 45
      },
      "Markdown": {
        "nFiles": 1,
        "blank": 4,
        "comment": 0,
        "code": 16
      },
      "ASP.NET": {
        "nFiles": 2,
        "blank": 0,
        "comment": 0,
        "code": 2
      },
      "SUM": {
        "blank": 9790,
        "comment": 3560,
        "code": 74318,
        "nFiles": 1180
      }
    }
  },
  {
    "date": "2017-11-1",
    "count": {
      "C#": {
        "nFiles": 941,
        "blank": 6841,
        "comment": 1103,
        "code": 54562
      },
      "C++": {
        "nFiles": 56,
        "blank": 1056,
        "comment": 49,
        "code": 7291
      },
      "C/C++ Header": {
        "nFiles": 104,
        "blank": 1400,
        "comment": 403,
        "code": 6582
      },
      "MSBuild script": {
        "nFiles": 19,
        "blank": 0,
        "comment": 132,
        "code": 3997
      },
      "PowerShell": {
        "nFiles": 9,
        "blank": 232,
        "comment": 739,
        "code": 782
      },
      "Razor": {
        "nFiles": 11,
        "blank": 5,
        "comment": 0,
        "code": 246
      },
      "Smalltalk": {
        "nFiles": 2,
        "blank": 13,
        "comment": 0,
        "code": 201
      },
      "CSS": {
        "nFiles": 1,
        "blank": 33,
        "comment": 0,
        "code": 190
      },
      "Markdown": {
        "nFiles": 2,
        "blank": 23,
        "comment": 0,
        "code": 88
      },
      "HTML": {
        "nFiles": 1,
        "blank": 1,
        "comment": 0,
        "code": 45
      },
      "ASP.NET": {
        "nFiles": 2,
        "blank": 0,
        "comment": 0,
        "code": 2
      },
      "SUM": {
        "blank": 9604,
        "comment": 2426,
        "code": 73986,
        "nFiles": 1148
      }
    }
  },
  {
    "date": "2017-12-1",
    "count": {
      "C#": {
        "nFiles": 1083,
        "blank": 8425,
        "comment": 2181,
        "code": 63273
      },
      "C++": {
        "nFiles": 65,
        "blank": 1185,
        "comment": 117,
        "code": 7967
      },
      "C/C++ Header": {
        "nFiles": 117,
        "blank": 1468,
        "comment": 407,
        "code": 6832
      },
      "MSBuild script": {
        "nFiles": 26,
        "blank": 0,
        "comment": 181,
        "code": 5153
      },
      "PowerShell": {
        "nFiles": 9,
        "blank": 233,
        "comment": 739,
        "code": 789
      },
      "Razor": {
        "nFiles": 11,
        "blank": 5,
        "comment": 0,
        "code": 246
      },
      "Smalltalk": {
        "nFiles": 2,
        "blank": 13,
        "comment": 0,
        "code": 205
      },
      "CSS": {
        "nFiles": 1,
        "blank": 33,
        "comment": 0,
        "code": 190
      },
      "Markdown": {
        "nFiles": 2,
        "blank": 23,
        "comment": 0,
        "code": 88
      },
      "HTML": {
        "nFiles": 1,
        "blank": 1,
        "comment": 0,
        "code": 45
      },
      "ASP.NET": {
        "nFiles": 2,
        "blank": 0,
        "comment": 0,
        "code": 2
      },
      "SUM": {
        "blank": 11386,
        "comment": 3625,
        "code": 84790,
        "nFiles": 1319
      }
    }
  },
  {
    "date": "2018-1-1",
    "count": {
      "C#": {
        "nFiles": 1092,
        "blank": 8298,
        "comment": 2615,
        "code": 62283
      },
      "C++": {
        "nFiles": 65,
        "blank": 1187,
        "comment": 117,
        "code": 8002
      },
      "C/C++ Header": {
        "nFiles": 119,
        "blank": 1470,
        "comment": 407,
        "code": 6859
      },
      "MSBuild script": {
        "nFiles": 26,
        "blank": 0,
        "comment": 181,
        "code": 5179
      },
      "PowerShell": {
        "nFiles": 9,
        "blank": 233,
        "comment": 739,
        "code": 789
      },
      "Razor": {
        "nFiles": 11,
        "blank": 5,
        "comment": 0,
        "code": 246
      },
      "Smalltalk": {
        "nFiles": 2,
        "blank": 13,
        "comment": 0,
        "code": 205
      },
      "CSS": {
        "nFiles": 1,
        "blank": 33,
        "comment": 0,
        "code": 190
      },
      "Markdown": {
        "nFiles": 2,
        "blank": 23,
        "comment": 0,
        "code": 88
      },
      "HTML": {
        "nFiles": 1,
        "blank": 1,
        "comment": 0,
        "code": 45
      },
      "ASP.NET": {
        "nFiles": 2,
        "blank": 0,
        "comment": 0,
        "code": 2
      },
      "SUM": {
        "blank": 11263,
        "comment": 4059,
        "code": 83888,
        "nFiles": 1330
      }
    }
  },
  {
    "date": "2018-2-1",
    "count": {
      "C#": {
        "nFiles": 1145,
        "blank": 8702,
        "comment": 2650,
        "code": 63905
      },
      "C++": {
        "nFiles": 65,
        "blank": 1191,
        "comment": 117,
        "code": 8040
      },
      "C/C++ Header": {
        "nFiles": 121,
        "blank": 1478,
        "comment": 407,
        "code": 6949
      },
      "MSBuild script": {
        "nFiles": 25,
        "blank": 0,
        "comment": 174,
        "code": 5125
      },
      "PowerShell": {
        "nFiles": 9,
        "blank": 233,
        "comment": 739,
        "code": 789
      },
      "Razor": {
        "nFiles": 11,
        "blank": 5,
        "comment": 0,
        "code": 246
      },
      "Smalltalk": {
        "nFiles": 2,
        "blank": 14,
        "comment": 0,
        "code": 208
      },
      "CSS": {
        "nFiles": 1,
        "blank": 33,
        "comment": 0,
        "code": 190
      },
      "Markdown": {
        "nFiles": 2,
        "blank": 23,
        "comment": 0,
        "code": 88
      },
      "HTML": {
        "nFiles": 1,
        "blank": 1,
        "comment": 0,
        "code": 45
      },
      "ASP.NET": {
        "nFiles": 2,
        "blank": 0,
        "comment": 0,
        "code": 2
      },
      "SUM": {
        "blank": 11680,
        "comment": 4087,
        "code": 85587,
        "nFiles": 1384
      }
    }
  },
  {
    "date": "2018-3-1",
    "count": {
      "C#": {
        "nFiles": 1199,
        "blank": 9043,
        "comment": 2290,
        "code": 67047
      },
      "C++": {
        "nFiles": 65,
        "blank": 1201,
        "comment": 117,
        "code": 8138
      },
      "C/C++ Header": {
        "nFiles": 124,
        "blank": 1491,
        "comment": 407,
        "code": 7033
      },
      "MSBuild script": {
        "nFiles": 27,
        "blank": 0,
        "comment": 188,
        "code": 5436
      },
      "PowerShell": {
        "nFiles": 9,
        "blank": 233,
        "comment": 739,
        "code": 789
      },
      "Razor": {
        "nFiles": 11,
        "blank": 5,
        "comment": 0,
        "code": 246
      },
      "Smalltalk": {
        "nFiles": 2,
        "blank": 16,
        "comment": 0,
        "code": 215
      },
      "CSS": {
        "nFiles": 1,
        "blank": 33,
        "comment": 0,
        "code": 190
      },
      "Markdown": {
        "nFiles": 2,
        "blank": 23,
        "comment": 0,
        "code": 88
      },
      "HTML": {
        "nFiles": 1,
        "blank": 1,
        "comment": 0,
        "code": 45
      },
      "ASP.NET": {
        "nFiles": 2,
        "blank": 0,
        "comment": 0,
        "code": 2
      },
      "SUM": {
        "blank": 12046,
        "comment": 3741,
        "code": 89229,
        "nFiles": 1443
      }
    }
  },
  {
    "date": "2018-4-1",
    "count": {
      "C#": {
        "nFiles": 1180,
        "blank": 9187,
        "comment": 2163,
        "code": 67595
      },
      "C++": {
        "nFiles": 65,
        "blank": 1201,
        "comment": 117,
        "code": 8138
      },
      "C/C++ Header": {
        "nFiles": 124,
        "blank": 1491,
        "comment": 407,
        "code": 7033
      },
      "MSBuild script": {
        "nFiles": 26,
        "blank": 0,
        "comment": 181,
        "code": 5217
      },
      "PowerShell": {
        "nFiles": 9,
        "blank": 230,
        "comment": 739,
        "code": 765
      },
      "Markdown": {
        "nFiles": 3,
        "blank": 78,
        "comment": 0,
        "code": 286
      },
      "Smalltalk": {
        "nFiles": 2,
        "blank": 18,
        "comment": 0,
        "code": 226
      },
      "Razor": {
        "nFiles": 2,
        "blank": 0,
        "comment": 0,
        "code": 51
      },
      "HTML": {
        "nFiles": 1,
        "blank": 1,
        "comment": 0,
        "code": 45
      },
      "ASP.NET": {
        "nFiles": 1,
        "blank": 0,
        "comment": 0,
        "code": 1
      },
      "SUM": {
        "blank": 12206,
        "comment": 3607,
        "code": 89357,
        "nFiles": 1413
      }
    }
  },
  {
    "date": "2018-5-1",
    "count": {
      "C#": {
        "nFiles": 1180,
        "blank": 9187,
        "comment": 2163,
        "code": 67595
      },
      "C++": {
        "nFiles": 65,
        "blank": 1201,
        "comment": 117,
        "code": 8138
      },
      "C/C++ Header": {
        "nFiles": 124,
        "blank": 1491,
        "comment": 407,
        "code": 7033
      },
      "MSBuild script": {
        "nFiles": 26,
        "blank": 0,
        "comment": 181,
        "code": 5217
      },
      "PowerShell": {
        "nFiles": 9,
        "blank": 230,
        "comment": 739,
        "code": 765
      },
      "Markdown": {
        "nFiles": 3,
        "blank": 78,
        "comment": 0,
        "code": 286
      },
      "Smalltalk": {
        "nFiles": 2,
        "blank": 18,
        "comment": 0,
        "code": 226
      },
      "Razor": {
        "nFiles": 2,
        "blank": 0,
        "comment": 0,
        "code": 51
      },
      "HTML": {
        "nFiles": 1,
        "blank": 1,
        "comment": 0,
        "code": 45
      },
      "ASP.NET": {
        "nFiles": 1,
        "blank": 0,
        "comment": 0,
        "code": 1
      },
      "SUM": {
        "blank": 12206,
        "comment": 3607,
        "code": 89357,
        "nFiles": 1413
      }
    }
  }
]